README.txt
setup.py
Products/__init__.py
Products.CMFSquidTool.egg-info/PKG-INFO
Products.CMFSquidTool.egg-info/SOURCES.txt
Products.CMFSquidTool.egg-info/dependency_links.txt
Products.CMFSquidTool.egg-info/entry_points.txt
Products.CMFSquidTool.egg-info/namespace_packages.txt
Products.CMFSquidTool.egg-info/not-zip-safe
Products.CMFSquidTool.egg-info/requires.txt
Products.CMFSquidTool.egg-info/top_level.txt
Products/CMFSquidTool/Permissions.py
Products/CMFSquidTool/SquidTool.py
Products/CMFSquidTool/__init__.py
Products/CMFSquidTool/config.py
Products/CMFSquidTool/configure.zcml
Products/CMFSquidTool/makefile.in
Products/CMFSquidTool/patch.py
Products/CMFSquidTool/queue.py
Products/CMFSquidTool/threadinglocal.py
Products/CMFSquidTool/tool.gif
Products/CMFSquidTool/utils.py
Products/CMFSquidTool/version.txt
Products/CMFSquidTool/Extensions/Install.py
Products/CMFSquidTool/i18n/squidtool-de.po
Products/CMFSquidTool/i18n/squidtool-es.po
Products/CMFSquidTool/i18n/squidtool-zh.po
Products/CMFSquidTool/i18n/squidtool.pot
Products/CMFSquidTool/profiles/default/metadata.xml
Products/CMFSquidTool/profiles/default/toolset.xml
Products/CMFSquidTool/skins/squid_tool/prefs_squid_tool.pt
Products/CMFSquidTool/tests/__init__.py
Products/CMFSquidTool/tests/base.py
Products/CMFSquidTool/tests/framework.py
Products/CMFSquidTool/tests/runalltests.py
Products/CMFSquidTool/tests/test.bat
Products/CMFSquidTool/tests/test_connections.py
Products/CMFSquidTool/tests/test_tool.py
Products/CMFSquidTool/www/config.zpt
docs/HISTORY.txt
docs/INSTALL.txt
docs/LICENSE.txt