Metadata-Version: 1.0
Name: Products.CMFSquidTool
Version: 1.5.1
Summary: HTTP cache management for CMF sites
Home-page: http://svn.plone.org/svn/collective/Products.CMFSquidTool/
Author: Simon Eisenmann and other
Author-email: plone-developers@lists.sourceforge.net
License: ZPL
Platform: UNKNOWN
Classifier: Framework :: Plone
Classifier: Programming Language :: Python
Classifier: Topic :: Software Development :: Libraries :: Python Modules
